pelican/plugins/feed_content_footer/__init__.py
pelican/plugins/feed_content_footer/feed_content_footer.py
pelican/plugins/feed_content_footer/tests/__init__.py
pelican/plugins/feed_content_footer/tests/content/foo.md
pelican/plugins/feed_content_footer/tests/content/test.md
pelican/plugins/feed_content_footer/tests/pelicanconf.py
pelican/plugins/feed_content_footer/tests/test_feed_content_footer.py
pelican_feed_content_footer-1.0.dist-info/LICENSE
pelican_feed_content_footer-1.0.dist-info/METADATA
pelican_feed_content_footer-1.0.dist-info/WHEEL
pelican_feed_content_footer-1.0.dist-info/RECORD
