Metadata-Version: 2.1
Name: pelican-feed-content-footer
Version: 1.0
Summary: Pelican plugin that adds a footer to RSS/Atom feed items content.
Home-page: https://tmb.codeberg.page/pelican-feed-content-footer/
License: AGPL-3.0-only
Author: Tobias Bölz
Author-email: tobias@boelz.eu
Requires-Python: >=3.10,<4.0
Classifier: Development Status :: 5 - Production/Stable
Classifier: Framework :: Pelican
Classifier: Framework :: Pelican :: Plugins
Classifier: Intended Audience :: End Users/Desktop
Classifier: License :: OSI Approved :: GNU Affero General Public License v3
Classifier: Operating System :: OS Independent
Classifier: Programming Language :: Python :: 3
Classifier: Programming Language :: Python :: 3.10
Classifier: Programming Language :: Python :: 3.11
Classifier: Programming Language :: Python :: 3.12
Classifier: Programming Language :: Python :: 3.13
Classifier: Topic :: Internet :: WWW/HTTP
Classifier: Topic :: Software Development :: Libraries :: Python Modules
Requires-Dist: pelican (>=4.5,<5.0)
Project-URL: Repository, https://git.boelz.eu/tmb/pelican-feed-content-footer/
